ncu/__init__.py
ncu/auto_docs.py
ncu/constants.py
ncu/update_version.py
nice_coding_utils-0.1.9.dist-info/licenses/LICENSE
nice_coding_utils-0.1.9.dist-info/METADATA
nice_coding_utils-0.1.9.dist-info/WHEEL
nice_coding_utils-0.1.9.dist-info/top_level.txt
nice_coding_utils-0.1.9.dist-info/RECORD
