Metadata-Version: 2.4
Name: nice-coding-utils
Version: 0.1.9
Summary: A bunch of utils for programmers.
Author-email: Justus <justus.d2025@gmail.com>
License:                     GNU GENERAL PUBLIC LICENSE
Project-URL: homepage, https://github.com/justusdecker/nice-coding-utils
Project-URL: documentation, https://github.com/justusdecker/nice-coding-utils/blob/main/docs/auto-docs.md
Requires-Python: >=3.8
License-File: LICENSE
Dynamic: license-file
